Day_3(full_adder)/full_adder.v
module full_adder(
    input wire a, b, cin,
    output wire sum, cout
);
    wire s1, c1, c2;

   
    xor g1(s1, a, b);       
    xor g2(sum, s1, cin);   

   
    and g3(c1, a, b);       
    and g4(c2, s1, cin);    
    or  g5(cout, c1, c2);   

endmodule

Day_3(full_adder)/tb_full_adder.v
module tb_full_adder;
    reg a, b, cin;
    wire sum, cout;
    full_adder U(
        .a(a), .b(b), .cin(cin), 
        .sum(sum), .cout(cout)
    );

    initial begin
        $dumpfile("tb_full_adder.vcd");
        $dumpvars(0, tb_full_adder);

       
        a=0; b=0; cin=0; #10;
        a=0; b=0; cin=1; #10;
        a=0; b=1; cin=0; #10;
        a=0; b=1; cin=1; #10;
        a=1; b=0; cin=0; #10;
        a=1; b=0; cin=1; #10;
        a=1; b=1; cin=0; #10; 
        a=1; b=1; cin=1; #10;
        
        $finish;
    end
endmodule

Day_3(full_adder)/tb_full_adder.vcd
$date
	Wed Nov 19 20:17:47 2025
$end
$version
	Icarus Verilog
$end
$timescale
	1s
$end
$scope module tb_full_adder $end
$var wire 1 ! sum $end
$var wire 1 " cout $end
$var reg 1 # a $end
$var reg 1 $ b $end
$var reg 1 % cin $end
$scope module U $end
$var wire 1 # a $end
$var wire 1 $ b $end
$var wire 1 & c1 $end
$var wire 1 ' c2 $end
$var wire 1 % cin $end
$var wire 1 " cout $end
$var wire 1 ( s1 $end
$var wire 1 ! sum $end
$upscope $end
$upscope $end
$enddefinitions $end
#0
$dumpvars
0(
0'
0&
0%
0$
0#
0"
0!
$end
#10
1!
1%
#20
1(
0%
1$
#30
1"
0!
1'
1%
#40
0"
1!
0'
0%
0$
1#
#50
1"
0!
1'
1%
#60
0'
0(
1&
0%
1$
#70
1!
1%
