Day-6(full_adder using half_adder)/half_adder.v
module half_adder(
    input a,b,
    output sum,carry
);
  
    xor x1(sum, a, b);

    and a1(carry, a, b);
endmodule

Day-6(full_adder using half_adder)/full_adder.v
module full_adder(
    input a,b,cin,
    output sum,cout
);
    wire s1,c1,c2; 

    half_adder HA1 (.a(a), .b(b), .sum(s1), .carry(c1));

    half_adder HA2 (.a(s1), .b(cin), .sum(sum), .carry(c2));

    or o1(cout, c1, c2);
endmodule

Day-6(full_adder using half_adder)/tb_full_adder.v
module tb_full_adder;
    reg a,b,cin;

    wire sum,cout;
    full_adder DUT (.a(a), .b(b), .cin(cin), .sum(sum), .cout(cout));

    
    initial begin
        $monitor("Time: %0t | A=%b, B=%b, Cin=%b | Sum=%b, Cout=%b", $time, a, b, cin, sum, cout);
    end

    initial begin
       
        $dumpfile("dump_full_adder.vcd");
        $dumpvars(0,tb_full_adder);

        a = 0; b = 0; cin = 0; #10
        a = 0; b = 0; cin = 0; #10;
        a = 0; b = 0; cin = 1; #10;
        a = 0; b = 1; cin = 0; #10;
        a = 0; b = 1; cin = 1; #10;
        a = 1; b = 0; cin = 0; #10;
        a = 1; b = 0; cin = 1; #10;
        a = 1; b = 1; cin = 0; #10;
        a = 1; b = 1; cin = 1; #10;
        $finish;
    end
endmodule

Day-6(full_adder using half_adder)/dump_full_adder.vcd
$date
	Mon Nov 24 20:06:27 2025
$end
$version
	Icarus Verilog
$end
$timescale
	1s
$end
$scope module tb_full_adder $end
$var wire 1 ! sum $end
$var wire 1 " cout $end
$var reg 1 # a $end
$var reg 1 $ b $end
$var reg 1 % cin $end
$scope module DUT $end
$var wire 1 # a $end
$var wire 1 $ b $end
$var wire 1 % cin $end
$var wire 1 " cout $end
$var wire 1 ! sum $end
$var wire 1 & s1 $end
$var wire 1 ' c2 $end
$var wire 1 ( c1 $end
$scope module HA1 $end
$var wire 1 # a $end
$var wire 1 $ b $end
$var wire 1 ( carry $end
$var wire 1 & sum $end
$upscope $end
$scope module HA2 $end
$var wire 1 & a $end
$var wire 1 % b $end
$var wire 1 ' carry $end
$var wire 1 ! sum $end
$upscope $end
$upscope $end
$upscope $end
$enddefinitions $end
#0
$dumpvars
0(
0'
0&
0%
0$
0#
0"
0!
$end
#20
1!
1%
#30
1&
0%
1$
#40
1"
0!
1'
1%
#50
0"
1!
0'
0%
0$
1#
#60
1"
0!
1'
1%
#70
0'
0&
1(
0%
1$
#80
1!
1%
