Day-5(full_sub)/full_sub.v
module full_subtractor_sop(
    input  a, b,bin, 
    output diff, bout
);


    xor u_diff(diff, a, b, bin);
    wire not_a;
    wire term1,term2,term3;

    not u_inv(not_a, a);
    and u_term1(term1, not_a, b);    
    and u_term2(term2, not_a, bin); 
    and u_term3(term3, b, bin);      

    or u_bout(bout, term1, term2, term3);

endmodule

Day-5(full_sub)/tb_full_sub.v
module full_subtractor_tb;

    reg a, b, bin;
   
    wire diff, bout;

    full_subtractor_sop uut (
        .a(a), 
        .b(b), 
        .bin(bin), 
        .diff(diff), 
        .bout(bout)
    );

   
    initial begin
    
        $dumpfile("dump_full_sub.vcd");
        $dumpvars(0, full_subtractor_tb);

        $monitor("Time=%0t | A=%b B=%b Bin=%b | Diff=%b Bout=%b", 
                 $time, a, b, bin, diff, bout);

    
        a = 0; b = 0; bin = 0; #10;
        a = 0; b = 0; bin = 1; #10;
        a = 0; b = 1; bin = 0; #10;
        a = 0; b = 1; bin = 1; #10;
        a = 1; b = 0; bin = 0; #10;
        a = 1; b = 0; bin = 1; #10;
        a = 1; b = 1; bin = 0; #10;
        a = 1; b = 1; bin = 1; #10;

        $finish;
    end

endmodule

Day-5(full_sub)/dump_full_sub.vcd
$date
	Sun Nov 23 19:14:31 2025
$end
$version
	Icarus Verilog
$end
$timescale
	1s
$end
$scope module full_subtractor_tb $end
$var wire 1 ! diff $end
$var wire 1 " bout $end
$var reg 1 # a $end
$var reg 1 $ b $end
$var reg 1 % bin $end
$scope module uut $end
$var wire 1 # a $end
$var wire 1 $ b $end
$var wire 1 % bin $end
$var wire 1 " bout $end
$var wire 1 ! diff $end
$var wire 1 & not_a $end
$var wire 1 ' term1 $end
$var wire 1 ( term2 $end
$var wire 1 ) term3 $end
$upscope $end
$upscope $end
$enddefinitions $end
#0
$dumpvars
0)
0(
0'
1&
0%
0$
0#
0"
0!
$end
#10
1"
1!
1(
1%
#20
0(
1'
0%
1$
#30
0!
1(
1)
1%
#40
0"
0(
0'
0)
1!
0&
0%
0$
1#
#50
0!
1%
#60
0%
1$
#70
1"
1!
1)
1%
